tortoise_gis/__init__.py
tortoise_gis/_pypika_functions.py
tortoise_gis/fields/__init__.py
tortoise_gis/fields/geometry_collection_field.py
tortoise_gis/fields/geometry_field.py
tortoise_gis/fields/line_string_field.py
tortoise_gis/fields/multi_line_string_field.py
tortoise_gis/fields/multi_point_field.py
tortoise_gis/fields/multi_polygon_field.py
tortoise_gis/fields/point_field.py
tortoise_gis/fields/polygon_field.py
tortoise_gis/functions.py
tortoise_gis-0.1.3.dist-info/LICENSE
tortoise_gis-0.1.3.dist-info/METADATA
tortoise_gis-0.1.3.dist-info/WHEEL
tortoise_gis-0.1.3.dist-info/RECORD
