Metadata-Version: 2.1
Name: tortoise-gis
Version: 0.1.3
Summary: Geometrical and Geographical support for Tortoise ORM.
Home-page: https://github.com/revensky/tortoise-gis
License: MIT
Keywords: Tortoise,GIS
Author: Eduardo Rezende
Author-email: eduardorbr7@gmail.com
Requires-Python: >=3.8,<4.0
Classifier: Development Status :: 3 - Alpha
Classifier: License :: OSI Approved :: MIT License
Classifier: Operating System :: OS Independent
Classifier: Programming Language :: Python :: 3
Classifier: Programming Language :: Python :: 3.8
Classifier: Programming Language :: Python :: 3.9
Classifier: Programming Language :: Python :: 3.10
Classifier: Programming Language :: Python :: 3.11
Requires-Dist: shapely (>=2.0.1,<3.0.0)
Requires-Dist: tortoise-orm (>=0.19.3,<0.20.0)
Project-URL: Repository, https://github.com/revensky/tortoise-gis.git
